nvidia/__init__.py
nvidia/nvshmem/__init__.py
nvidia/nvshmem/include/__init__.py
nvidia/nvshmem/include/nvshmem.h
nvidia/nvshmem/include/nvshmemx.h
nvidia/nvshmem/include/bootstrap_device_host/nvshmem_uniqueid.h
nvidia/nvshmem/include/device/nvshmem_coll_defines.cuh
nvidia/nvshmem/include/device/nvshmem_defines.h
nvidia/nvshmem/include/device/nvshmem_device_macros.h
nvidia/nvshmem/include/device/nvshmemx_coll_defines.cuh
nvidia/nvshmem/include/device/nvshmemx_collective_launch_apis.h
nvidia/nvshmem/include/device/nvshmemx_defines.h
nvidia/nvshmem/include/device_host/nvshmem_common.cuh
nvidia/nvshmem/include/device_host/nvshmem_proxy_channel.h
nvidia/nvshmem/include/device_host/nvshmem_types.h
nvidia/nvshmem/include/device_host_transport/nvshmem_common_ibgda.h
nvidia/nvshmem/include/device_host_transport/nvshmem_common_transport.h
nvidia/nvshmem/include/device_host_transport/nvshmem_constants.h
nvidia/nvshmem/include/host/nvshmem_api.h
nvidia/nvshmem/include/host/nvshmem_coll_api.h
nvidia/nvshmem/include/host/nvshmem_macros.h
nvidia/nvshmem/include/host/nvshmemx_api.h
nvidia/nvshmem/include/host/nvshmemx_coll_api.h
nvidia/nvshmem/include/non_abi/nvshmem_build_options.h
nvidia/nvshmem/include/non_abi/nvshmem_version.h
nvidia/nvshmem/include/non_abi/nvshmemx_error.h
nvidia/nvshmem/include/non_abi/device/coll/alltoall.cuh
nvidia/nvshmem/include/non_abi/device/coll/barrier.cuh
nvidia/nvshmem/include/non_abi/device/coll/broadcast.cuh
nvidia/nvshmem/include/non_abi/device/coll/defines.cuh
nvidia/nvshmem/include/non_abi/device/coll/fcollect.cuh
nvidia/nvshmem/include/non_abi/device/coll/reduce.cuh
nvidia/nvshmem/include/non_abi/device/coll/reducescatter.cuh
nvidia/nvshmem/include/non_abi/device/coll/utils.cuh
nvidia/nvshmem/include/non_abi/device/common/nvshmemi_common_device.cuh
nvidia/nvshmem/include/non_abi/device/pt-to-pt/ibgda_device.cuh
nvidia/nvshmem/include/non_abi/device/pt-to-pt/nvshmemi_transfer_api.cuh
nvidia_nvshmem_cu11-3.2.5.dist-info/License.txt
nvidia_nvshmem_cu11-3.2.5.dist-info/METADATA
nvidia_nvshmem_cu11-3.2.5.dist-info/WHEEL
nvidia_nvshmem_cu11-3.2.5.dist-info/top_level.txt
nvidia_nvshmem_cu11-3.2.5.dist-info/RECORD
